{
  "id": "Closeable_MultipleClose",
  "formalism": "ere",
  "domain": "io",
  "signature": {
    "name": "Closeable_MultipleClose",
    "parameters": [
      {
        "type": "Closeable",
        "name": "c"
      }
    ]
  },
  "ir": {
    "events": [
      {
        "body": {
          "methods": [
            {
              "action": "event",
              "name": "close",
              "timing": "before",
              "parameters": [
                {
                  "type": "Closeable",
                  "name": "c"
                }
              ],
              "procediments": ":",
              "function": [
                {
                  "name": "call",
                  "arguments": [
                    {
                      "value": "* Closeable+.close(..)"
                    }
                  ]
                },
                {
                  "name": "target",
                  "arguments": [
                    {
                      "value": "c"
                    }
                  ]
                }
              ],
              "operation": [
                "&&"
              ]
            }
          ]
        }
      }
    ],
    "ere": {
      "expression": "close close+"
    },
    "violation": {
      "tag": "match",
      "body": {
        "statements": [
          {
            "type": "log",
            "level": "CRITICAL",
            "message": "__DEFAULT_MESSAGE"
          },
          {
            "type": "log",
            "level": "CRITICAL",
            "message": "\"close() was invoked multiple times.\""
          }
        ],
        "has_reset": false
      }
    }
  }
}