{
  "id": "Enumeration_Obsolete",
  "formalism": "ere",
  "domain": "util",
  "signature": {
    "name": "Enumeration_Obsolete",
    "parameters": [
      {
        "type": "Enumeration",
        "name": "e"
      }
    ]
  },
  "ir": {
    "events": [
      {
        "body": {
          "methods": [
            {
              "action": "event",
              "name": "use",
              "timing": "before",
              "parameters": [
                {
                  "type": "Enumeration",
                  "name": "e"
                }
              ],
              "procediments": ":",
              "function": [
                {
                  "name": "call",
                  "arguments": [
                    {
                      "value": "* Enumeration+.*(..)"
                    }
                  ]
                },
                {
                  "name": "target",
                  "arguments": [
                    {
                      "value": "e"
                    }
                  ]
                }
              ],
              "operation": [
                "&&"
              ]
            }
          ]
        }
      }
    ],
    "ere": {
      "expression": "use"
    },
    "violation": {
      "tag": "match",
      "body": {
        "statements": [
          {
            "type": "log",
            "level": "CRITICAL",
            "message": "__DEFAULT_MESSAGE"
          },
          {
            "type": "log",
            "level": "CRITICAL",
            "message": "\"The Enumeration interface is obsolete. New implementations should consider using the Interface interface.\""
          }
        ],
        "has_reset": false
      }
    }
  }
}